Workbook

Sheet README
A1: McLeod et al. (2022) Table II → 한국어 연역 후보 사전 (초안)
A3: 출처: McLeod, Sears, Chandler, Payne & Brigham (2022), Journal of Management Studies 59(7), Table II (pp.1671–1673). 원문 891개 중 890개 전사(PDF 줄바꿈으로 1개 차이 가능).
A4: 성격: 원 논문 절차 중 ② 연역 단계(Rodale 유의어)에 해당하는 '후보' 목록. 한국어 번역은 Claude 초안이며 확정 사전이 아님.
A5: 다음 단계: ③ DIPS 사업계획서 귀납 후보 추가 → ④ 평정자 3인 판정(Holsti ≥ .70) → ⑤ 외부 전문가 추가 제안 + 5인 만장일치.
A7: 시트 구성
A8: 후보사전_원어별: Table II 원어 1개당 한국어 후보 1행(후보가 여럿이면 여러 행). 평정자 판정 입력용.
A9: 고유키_요약: 형태소 매칭 키 기준으로 중복을 합친 목록. 실제 CATA 집계에 쓰일 사전의 모양.
A10: 집계: 차원별 후보 수·플래그 수·채택 수 (평정 입력에 따라 자동 갱신).
A12: 열 설명
A13: 형태소 분석: Kiwi(kiwipiepy) 분석 결과 전체. 매칭 키: 내용 형태소(NNG·VV·VA·XR 등)만 남긴 것 = 사업계획서에서 이 키와 일치하는 형태소를 셈.
A14: 예: '증가예정' → 증가/NNG + 예정/NNG 로 분석되므로 키 '증가/NNG'가 잡힘. '도와' → 돕/VV 로 원형 복원.
A15: 접두사(XPN)는 키에 포함: '비호감' = 비/XPN + 호감/NNG 이므로 '호감'(ethos)과 구별됨. 집계 시 긴 키(구 매칭)를 먼저 세고, 그 형태소는 짧은 키로 중복 집계하지 않음.
... A23: 입력 예시: 평정자1=유지, 평정자2=유지, 평정자3=제외, 비고='제조 맥락에서 logos' → 만장일치=제외

Sheet 후보사전_원어별
A1: No | B1: 차원 | C1: 테마(Table II) | D1: 원어(Table II) | E1: 한국어 후보 | F1: 형태소 분석(Kiwi) | G1: 매칭 키 | H1: 자동 플래그 | I1: 검토 메모 | J1: 평정자1 | K1: 평정자2 | L1: 평정자3 | M1: 만장일치 | N1: 비고
A2: 1 | B2: Logos(논리) | C2: logic | D2: logic | E2: 논리 | F2: 논리/NNG | G2: 논리/NNG | M2: =IF(COUNTA(J2:L2)<3,"",IF(COUNTIF(J2:L2,"유지")=3,"채택","제외"))
A3: 2 | B3: Logos(논리) | C3: logic | D3: reason | E3: 근거 | F3: 근거/NNG | G3: 근거/NNG | M3: =IF(COUNTA(J3:L3)<3,"",IF(COUNTIF(J3:L3,"유지")=3,"채택","제외"))
A4: 3 | B4: Logos(논리) | C4: logic | D4: reason | E4: 이유 | F4: 이유/NNG | G4: 이유/NNG | M4: =IF(COUNTA(J4:L4)<3,"",IF(COUNTIF(J4:L4,"유지")=3,"채택","제외"))
A5: 4 | B5: Logos(논리) | C5: logic | D5: judicious | E5: 신중 | F5: 신중/NNG | G5: 신중/NNG | H5: 차원충돌:ethos·logos·pathos | I5: logos(judicious)·pathos(cautious)·ethos(prudence, discreet)에 모두 대응 → 차원 배정 평정 필요 | M5: =IF(COUNTA(J5:L5)<3,"",IF(COUNTIF(J5:L5,"유지")=3,"채택","제외"))
A6: 5 | B6: Logos(논리) | C6: logic | D6: logistic | E6: 물류 | F6: 물류/NNG | G6: 물류/NNG | M6: =IF(COUNTA(J6:L6)<3,"",IF(COUNTIF(J6:L6,"유지")=3,"채택","제외"))
A7: 6 | B7: Logos(논리) | C7: logic | D7: politic | E7: 타당 | F7: 타당/NNG | G7: 타당/NNG | M7: =IF(COUNTA(J7:L7)<3,"",IF(COUNTIF(J7:L7,"유지")=3,"채택","제외"))
A8: 7 | B8: Logos(논리) | C8: logic | D8: astute | E8: 예리 | F8: 예리/NNP | G8: 예리/NNP | H8: 차원충돌:ethos·logos | M8: =IF(COUNTA(J8:L8)<3,"",IF(COUNTIF(J8:L8,"유지")=3,"채택","제외"))
A9: 8 | B9: Logos(논리) | C9: logic | D9: infer | E9: 추론 | F9: 추론/NNG | G9: 추론/NNG | M9: =IF(COUNTA(J9:L9)<3,"",IF(COUNTIF(J9:L9,"유지")=3,"채택","제외"))
A10: 9 | B10: Logos(논리) | C10: logic | D10: cogent | E10: 설득력 | F10: 설득력/NNG | G10: 설득력/NNG | M10: =IF(COUNTA(J10:L10)<3,"",IF(COUNTIF(J10:L10,"유지")=3,"채택","제외"))
A11: 10 | B11: Logos(논리) | C11: logic | D11: synthesis | E11: 종합 | F11: 종합/NNG | G11: 종합/NNG | M11: =IF(COUNTA(J11:L11)<3,"",IF(COUNTIF(J11:L11,"유지")=3,"채택","제외"))
A12: 11 | B12: Logos(논리) | C12: logic | D12: sane | E12: 건전 | F12: 건전/NNG | G12: 건전/NNG | H12: 차원충돌:ethos·logos | I12: logos(sane)·ethos(wholesome) 양쪽; '재무 건전성'은 logos | M12: =IF(COUNTA(J12:L12)<3,"",IF(COUNTIF(J12:L12,"유지")=3,"채택","제외"))
A13: 12 | B13: Logos(논리) | C13: logic | D13: sound-judgment | E13: 건전한 판단 | F13: 건전/NNG + 하/XSA + ᆫ/ETM + 판단/NNG | G13: 건전/NNG + 판단/NNG | H13: 구(句) 매칭 | M13: =IF(COUNTA(J13:L13)<3,"",IF(COUNTIF(J13:L13,"유지")=3,"채택","제외"))
A14: 13 | B14: Logos(논리) | C14: logic | D14: good-sense | E14: 양식 | F14: 양식/NNG | G14: 양식/NNG | M14: =IF(COUNTA(J14:L14)<3,"",IF(COUNTIF(J14:L14,"유지")=3,"채택","제외"))
A15: 14 | B15: Logos(논리) | C15: logic | D15: sober | E15: 냉철 | F15: 냉철/XR | G15: 냉철/XR | M15: =IF(COUNTA(J15:L15)<3,"",IF(COUNTIF(J15:L15,"유지")=3,"채택","제외"))
A16: 15 | B16: Logos(논리) | C16: logic | D16: presence-of-mind | E16: 침착 | F16: 침착/NNG | G16: 침착/NNG | M16: =IF(COUNTA(J16:L16)<3,"",IF(COUNTIF(J16:L16,"유지")=3,"채택","제외"))
A17: 16 | B17: Logos(논리) | C17: logic | D17: analytic | E17: 분석 | F17: 분석/NNG | G17: 분석/NNG | H17: 차원내 중복 | M17: =IF(COUNTA(J17:L17)<3,"",IF(COUNTIF(J17:L17,"유지")=3,"채택","제외"))
A18: 17 | B18: Logos(논리) | C18: logic | D18: common-sense | E18: 상식 | F18: 상식/NNG | G18: 상식/NNG | M18: =IF(COUNTA(J18:L18)<3,"",IF(COUNTIF(J18:L18,"유지")=3,"채택","제외"))
A19: 18 | B19: Logos(논리) | C19: logic | D19: deductive | E19: 연역 | F19: 연역/NNG | G19: 연역/NNG | M19: =IF(COUNTA(J19:L19)<3,"",IF(COUNTIF(J19:L19,"유지")=3,"채택","제외"))
A20: 19 | B20: Logos(논리) | C20: logic | D20: inductive | E20: 귀납 | F20: 귀납/NNG | G20: 귀납/NNG | M20: =IF(COUNTA(J20:L20)<3,"",IF(COUNTIF(J20:L20,"유지")=3,"채택","제외"))
A21: 20 | B21: Logos(논리) | C21: logic | D21: consequence | E21: 결과 | F21: 결과/NNG | G21: 결과/NNG | M21: =IF(COUNTA(J21:L21)<3,"",IF(COUNTIF(J21:L21,"유지")=3,"채택","제외"))
A22: 21 | B22: Logos(논리) | C22: logic | D22: rational | E22: 합리 | F22: 합리/NNG | G22: 합리/NNG | M22: =IF(COUNTA(J22:L22)<3,"",IF(COUNTIF(J22:L22,"유지")=3,"채택","제외"))
A23: 22 | B23: Logos(논리) | C23: logic | D23: practical | E23: 실용 | F23: 실용/NNG | G23: 실용/NNG | H23: 차원내 중복 | M23: =IF(COUNTA(J23:L23)<3,"",IF(COUNTIF(J23:L23,"유지")=3,"채택","제외"))
A24: 23 | B24: Logos(논리) | C24: logic | D24: practical | E24: 실질 | F24: 실질/NNG | G24: 실질/NNG | H24: 차원내 중복 | M24: =IF(COUNTA(J24:L24)<3,"",IF(COUNTIF(J24:L24,"유지")=3,"채택","제외"))
A25: 24 | B25: Logos(논리) | C25: logic | D25: pragmatic | E25: 실용적 | F25: 실용/NNG + 적/XSN | G25: 실용/NNG | H25: 차원내 중복 | M25: =IF(COUNTA(J25:L25)<3,"",IF(COUNTIF(J25:L25,"유지")=3,"채택","제외"))
A26: 25 | B26: Logos(논리) | C26: logic | D26: sensible | E26: 합당 | F26: 합당/NNG | G26: 합당/NNG | M26: =IF(COUNTA(J26:L26)<3,"",IF(COUNTIF(J26:L26,"유지")=3,"채택","제외"))
A27: 26 | B27: Logos(논리) | C27: logic | D27: advisable | E27: 바람직 | F27: 바람직/XR | G27: 바람직/XR | M27: =IF(COUNTA(J27:L27)<3,"",IF(COUNTIF(J27:L27,"유지")=3,"채택","제외"))
A28: 27 | B28: Logos(논리) | C28: logic | D28: well-advised | E28: 적절한 판단 | F28: 적절/XR + 하/XSA + ᆫ/ETM + 판단/NNG | G28: 적절/XR + 판단/NNG | H28: 구(句) 매칭 | M28: =IF(COUNTA(J28:L28)<3,"",IF(COUNTIF(J28:L28,"유지")=3,"채택","제외"))
A29: 28 | B29: Logos(논리) | C29: logic | D29: well-argued | E29: 논거 | F29: 논거/NNG | G29: 논거/NNG | M29: =IF(COUNTA(J29:L29)<3,"",IF(COUNTIF(J29:L29,"유지")=3,"채택","제외"))
A30: 29 | B30: Logos(논리) | C30: logic | D30: well-grounded | E30: 근거 탄탄 | F30: 근거/NNG + 탄탄/XR | G30: 근거/NNG + 탄탄/XR | H30: 구(句) 매칭 | M30: =IF(COUNTA(J30:L30)<3,"",IF(COUNTIF(J30:L30,"유지")=3,"채택","제외"))
A31: 30 | B31: Logos(논리) | C31: logic | D31: well-founded | E31: 근거 있는 | F31: 근거/NNG + 있/VA + 는/ETM | G31: 근거/NNG + 있/VA | H31: 구(句) 매칭 | M31: =IF(COUNTA(J31:L31)<3,"",IF(COUNTIF(J31:L31,"유지")=3,"채택","제외"))
A32: 31 | B32: Logos(논리) | C32: logic | D32: plausible | E32: 타당성 | F32: 타당성/NNG | G32: 타당성/NNG | M32: =IF(COUNTA(J32:L32)<3,"",IF(COUNTIF(J32:L32,"유지")=3,"채택","제외"))
A33: 32 | B33: Logos(논리) | C33: efficiency | D33: efficiency | E33: 효율 | F33: 효율/NNG | G33: 효율/NNG | M33: =IF(COUNTA(J33:L33)<3,"",IF(COUNTIF(J33:L33,"유지")=3,"채택","제외"))
A34: 33 | B34: Logos(논리) | C34: efficiency | D34: yield | E34: 수율 | F34: 수율/NNG | G34: 수율/NNG | I34: yield. 제조업 핵심 지표 → logos | M34: =IF(COUNTA(J34:L34)<3,"",IF(COUNTIF(J34:L34,"유지")=3,"채택","제외"))
A35: 34 | B35: Logos(논리) | C35: efficiency | D35: yield | E35: 수익률 | F35: 수익/NNG + 률/XSN | G35: 수익/NNG | H35: 차원내 중복 | M35: =IF(COUNTA(J35:L35)<3,"",IF(COUNTIF(J35:L35,"유지")=3,"채택","제외"))
A36: 35 | B36: Logos(논리) | C36: efficiency | D36: minimum | E36: 최소 | F36: 최소/NNG | G36: 최소/NNG | M36: =IF(COUNTA(J36:L36)<3,"",IF(COUNTIF(J36:L36,"유지")=3,"채택","제외"))
A37: 36 | B37: Logos(논리) | C37: efficiency | D37: maximum | E37: 최대 | F37: 최대/NNG | G37: 최대/NNG | M37: =IF(COUNTA(J37:L37)<3,"",IF(COUNTIF(J37:L37,"유지")=3,"채택","제외"))
A38: 37 | B38: Logos(논리) | C38: efficiency | D38: bargain | E38: 저가 | F38: 저가/NNG | G38: 저가/NNG | M38: =IF(COUNTA(J38:L38)<3,"",IF(COUNTIF(J38:L38,"유지")=3,"채택","제외"))
A39: 38 | B39: Logos(논리) | C39: efficiency | D39: rate | E39: 비율 | F39: 비율/NNG | G39: 비율/NNG | M39: =IF(COUNTA(J39:L39)<3,"",IF(COUNTIF(J39:L39,"유지")=3,"채택","제외"))
A40: 39 | B40: Logos(논리) | C40: efficiency | D40: stabilize | E40: 안정화 | F40: 안정/NNG + 화/XSN | G40: 안정/NNG | M40: =IF(COUNTA(J40:L40)<3,"",IF(COUNTIF(J40:L40,"유지")=3,"채택","제외"))
A41: 40 | B41: Logos(논리) | C41: efficiency | D41: steady | E41: 꾸준 | F41: 꾸준/XR | G41: 꾸준/XR | M41: =IF(COUNTA(J41:L41)<3,"",IF(COUNTIF(J41:L41,"유지")=3,"채택","제외"))
A42: 41 | B42: Logos(논리) | C42: efficiency | D42: supply | E42: 공급 | F42: 공급/NNG | G42: 공급/NNG | M42: =IF(COUNTA(J42:L42)<3,"",IF(COUNTIF(J42:L42,"유지")=3,"채택","제외"))
A43: 42 | B43: Logos(논리) | C43: efficiency | D43: reduce | E43: 감소 | F43: 감소/NNG | G43: 감소/NNG | M43: =IF(COUNTA(J43:L43)<3,"",IF(COUNTIF(J43:L43,"유지")=3,"채택","제외"))
A44: 43 | B44: Logos(논리) | C44: efficiency | D44: reduce | E44: 절감 | F44: 절감/NNG | G44: 절감/NNG | M44: =IF(COUNTA(J44:L44)<3,"",IF(COUNTIF(J44:L44,"유지")=3,"채택","제외"))
A45: 44 | B45: Logos(논리) | C45: efficiency | D45: residual | E45: 잔여 | F45: 잔여/NNG | G45: 잔여/NNG | M45: =IF(COUNTA(J45:L45)<3,"",IF(COUNTIF(J45:L45,"유지")=3,"채택","제외"))
A46: 45 | B46: Logos(논리) | C46: efficiency | D46: consolidate | E46: 통합 | F46: 통합/NNG | G46: 통합/NNG | M46: =IF(COUNTA(J46:L46)<3,"",IF(COUNTIF(J46:L46,"유지")=3,"채택","제외"))
A47: 46 | B47: Logos(논리) | C47: efficiency | D47: generate | E47: 창출 | F47: 창출/NNG | G47: 창출/NNG | M47: =IF(COUNTA(J47:L47)<3,"",IF(COUNTIF(J47:L47,"유지")=3,"채택","제외"))
... A50: 49 | B50: Logos(논리) | C50: efficiency | D50: prepare | E50: 준비 | F50: 준비/NNG | G50: 준비/NNG | M50: =IF(COUNTA(J50:L50)<3,"",IF(COUNTIF(J50:L50,"유지")=3,"채택","제외"))
A51: 50 | B51: Logos(논리) | C51: efficiency | D51: productive | E51: 생산적 | F51: 생산/NNG + 적/XSN | G51: 생산/NNG | H51: 차원내 중복 | M51: =IF(COUNTA(J51:L51)<3,"",IF(COUNTIF(J51:L51,"유지")=3,"채택","제외"))
A52: 51 | B52: Logos(논리) | C52: efficiency | D52: produce | E52: 생산 | F52: 생산/NNG | G52: 생산/NNG | H52: 차원내 중복 | M52: =IF(COUNTA(J52:L52)<3,"",IF(COUNTIF(J52:L52,"유지")=3,"채택","제외"))
A53: 52 | B53: Logos(논리) | C53: efficiency | D53: adept | E53: 능숙 | F53: 능숙/XR | G53: 능숙/XR | M53: =IF(COUNTA(J53:L53)<3,"",IF(COUNTIF(J53:L53,"유지")=3,"채택","제외"))
A54: 53 | B54: Logos(논리) | C54: efficiency | D54: economic | E54: 경제 | F54: 경제/NNG | G54: 경제/NNG | M54: =IF(COUNTA(J54:L54)<3,"",IF(COUNTIF(J54:L54,"유지")=3,"채택","제외"))
A55: 54 | B55: Logos(논리) | C55: efficiency | D55: metric | E55: 지표 | F55: 지표/NNG | G55: 지표/NNG | M55: =IF(COUNTA(J55:L55)<3,"",IF(COUNTIF(J55:L55,"유지")=3,"채택","제외"))
A56: 55 | B56: Logos(논리) | C56: efficiency | D56: deficiency | E56: 부족 | F56: 부족/NNG | G56: 부족/NNG | M56: =IF(COUNTA(J56:L56)<3,"",IF(COUNTIF(J56:L56,"유지")=3,"채택","제외"))
A57: 56 | B57: Logos(논리) | C57: efficiency | D57: deficiency | E57: 결함 | F57: 결함/NNG | G57: 결함/NNG | M57: =IF(COUNTA(J57:L57)<3,"",IF(COUNTIF(J57:L57,"유지")=3,"채택","제외"))
A58: 57 | B58: Logos(논리) | C58: efficiency | D58: cost | E58: 비용 | F58: 비용/NNG | G58: 비용/NNG | H58: 차원내 중복 | M58: =IF(COUNTA(J58:L58)<3,"",IF(COUNTIF(J58:L58,"유지")=3,"채택","제외"))
A59: 58 | B59: Logos(논리) | C59: efficiency | D59: cost | E59: 원가 | F59: 원가/NNG | G59: 원가/NNG | M59: =IF(COUNTA(J59:L59)<3,"",IF(COUNTIF(J59:L59,"유지")=3,"채택","제외"))
A60: 59 | B60: Logos(논리) | C60: efficiency | D60: capacity | E60: 용량 | F60: 용량/NNG | G60: 용량/NNG | M60: =IF(COUNTA(J60:L60)<3,"",IF(COUNTIF(J60:L60,"유지")=3,"채택","제외"))
A61: 60 | B61: Logos(논리) | C61: efficiency | D61: capacity | E61: 생산능력 | F61: 생산/NNG + 능력/NNG | G61: 생산/NNG + 능력/NNG | H61: 구(句) 매칭 | M61: =IF(COUNTA(J61:L61)<3,"",IF(COUNTIF(J61:L61,"유지")=3,"채택","제외"))
A62: 61 | B62: Logos(논리) | C62: effective | D62: effective | E62: 효과 | F62: 효과/NNG | G62: 효과/NNG | H62: 차원내 중복 | I62: effective·effect 중복 매핑 | M62: =IF(COUNTA(J62:L62)<3,"",IF(COUNTIF(J62:L62,"유지")=3,"채택","제외"))
A63: 62 | B63: Logos(논리) | C63: effective | D63: allowance | E63: 허용 | F63: 허용/NNG | G63: 허용/NNG | M63: =IF(COUNTA(J63:L63)<3,"",IF(COUNTIF(J63:L63,"유지")=3,"채택","제외"))
A64: 63 | B64: Logos(논리) | C64: effective | D64: contingent | E64: 조건부 | F64: 조건부/NNG | G64: 조건부/NNG | M64: =IF(COUNTA(J64:L64)<3,"",IF(COUNTIF(J64:L64,"유지")=3,"채택","제외"))
A65: 64 | B65: Logos(논리) | C65: effective | D65: award | E65: 수상 | F65: 수상/NNG | G65: 수상/NNG | M65: =IF(COUNTA(J65:L65)<3,"",IF(COUNTIF(J65:L65,"유지")=3,"채택","제외"))
A66: 65 | B66: Logos(논리) | C66: effective | D66: reward | E66: 보상 | F66: 보상/NNG | G66: 보상/NNG | H66: 차원내 중복 | I66: reward·recompense 중복 | M66: =IF(COUNTA(J66:L66)<3,"",IF(COUNTIF(J66:L66,"유지")=3,"채택","제외"))
A67: 66 | B67: Logos(논리) | C67: effective | D67: eligible | E67: 자격요건 | F67: 자격/NNG + 요건/NNG | G67: 자격/NNG + 요건/NNG | H67: 구(句) 매칭 | M67: =IF(COUNTA(J67:L67)<3,"",IF(COUNTIF(J67:L67,"유지")=3,"채택","제외"))
A68: 67 | B68: Logos(논리) | C68: effective | D68: realize | E68: 실현 | F68: 실현/NNG | G68: 실현/NNG | M68: =IF(COUNTA(J68:L68)<3,"",IF(COUNTIF(J68:L68,"유지")=3,"채택","제외"))
A69: 68 | B69: Logos(논리) | C69: effective | D69: retain | E69: 유지 | F69: 유지/NNG | G69: 유지/NNG | M69: =IF(COUNTA(J69:L69)<3,"",IF(COUNTIF(J69:L69,"유지")=3,"채택","제외"))
A70: 69 | B70: Logos(논리) | C70: effective | D70: benefit | E70: 이점 | F70: 이점/NNG | G70: 이점/NNG | H70: 차원내 중복 | I70: 단독 분석 시 '이/MM + 점'으로 잘못 쪼개져 수동 보정 | M70: =IF(COUNTA(J70:L70)<3,"",IF(COUNTIF(J70:L70,"유지")=3,"채택","제외"))
A71: 70 | B71: Logos(논리) | C71: effective | D71: benefit | E71: 혜택 | F71: 혜택/NNG | G71: 혜택/NNG | M71: =IF(COUNTA(J71:L71)<3,"",IF(COUNTIF(J71:L71,"유지")=3,"채택","제외"))
A72: 71 | B72: Logos(논리) | C72: effective | D72: notable | E72: 주목 | F72: 주목/NNG | G72: 주목/NNG | M72: =IF(COUNTA(J72:L72)<3,"",IF(COUNTIF(J72:L72,"유지")=3,"채택","제외"))
A73: 72 | B73: Logos(논리) | C73: effective | D73: persistent | E73: 지속 | F73: 지속/NNG | G73: 지속/NNG | M73: =IF(COUNTA(J73:L73)<3,"",IF(COUNTIF(J73:L73,"유지")=3,"채택","제외"))
A74: 73 | B74: Logos(논리) | C74: effective | D74: responsible | E74: 책임 | F74: 책임/NNG | G74: 책임/NNG | M74: =IF(COUNTA(J74:L74)<3,"",IF(COUNTIF(J74:L74,"유지")=3,"채택","제외"))
A75: 74 | B75: Logos(논리) | C75: effective | D75: effectual | E75: 유효 | F75: 유효/NNG | G75: 유효/NNG | M75: =IF(COUNTA(J75:L75)<3,"",IF(COUNTIF(J75:L75,"유지")=3,"채택","제외"))
A76: 75 | B76: Logos(논리) | C76: effective | D76: adequate | E76: 적정 | F76: 적정/NNG | G76: 적정/NNG | M76: =IF(COUNTA(J76:L76)<3,"",IF(COUNTIF(J76:L76,"유지")=3,"채택","제외"))
A77: 76 | B77: Logos(논리) | C77: effective | D77: sufficient | E77: 충분 | F77: 충분/XR | G77: 충분/XR | M77: =IF(COUNTA(J77:L77)<3,"",IF(COUNTIF(J77:L77,"유지")=3,"채택","제외"))
A78: 77 | B78: Logos(논리) | C78: effective | D78: function | E78: 기능 | F78: 기능/NNG | G78: 기능/NNG | M78: =IF(COUNTA(J78:L78)<3,"",IF(COUNTIF(J78:L78,"유지")=3,"채택","제외"))
A79: 78 | B79: Logos(논리) | C79: effective | D79: operate | E79: 운영 | F79: 운영/NNG | G79: 운영/NNG | M79: =IF(COUNTA(J79:L79)<3,"",IF(COUNTIF(J79:L79,"유지")=3,"채택","제외"))
A80: 79 | B80: Logos(논리) | C80: effective | D80: operate | E80: 가동 | F80: 가동/NNG | G80: 가동/NNG | M80: =IF(COUNTA(J80:L80)<3,"",IF(COUNTIF(J80:L80,"유지")=3,"채택","제외"))
A81: 80 | B81: Logos(논리) | C81: effective | D81: actual | E81: 실제 | F81: 실제/NNG | G81: 실제/NNG | M81: =IF(COUNTA(J81:L81)<3,"",IF(COUNTIF(J81:L81,"유지")=3,"채택","제외"))
A82: 81 | B82: Logos(논리) | C82: effective | D82: real | E82: 실질 | F82: 실질/NNG | G82: 실질/NNG | H82: 차원내 중복 | M82: =IF(COUNTA(J82:L82)<3,"",IF(COUNTIF(J82:L82,"유지")=3,"채택","제외"))
A83: 82 | B83: Logos(논리) | C83: effective | D83: effect | E83: 효과 | F83: 효과/NNG | G83: 효과/NNG | H83: 차원내 중복 | I83: effective·effect 중복 매핑 | M83: =IF(COUNTA(J83:L83)<3,"",IF(COUNTIF(J83:L83,"유지")=3,"채택","제외"))
A84: 83 | B84: Logos(논리) | C84: profitability | D84: profitability | E84: 수익성 | F84: 수익/NNG + 성/XSN | G84: 수익/NNG | H84: 차원내 중복 | M84: =IF(COUNTA(J84:L84)<3,"",IF(COUNTIF(J84:L84,"유지")=3,"채택","제외"))
A85: 84 | B85: Logos(논리) | C85: profitability | D85: account | E85: 계정 | F85: 계정/NNG | G85: 계정/NNG | M85: =IF(COUNTA(J85:L85)<3,"",IF(COUNTIF(J85:L85,"유지")=3,"채택","제외"))
A86: 85 | B86: Logos(논리) | C86: profitability | D86: expense | E86: 비용 | F86: 비용/NNG | G86: 비용/NNG | H86: 차원내 중복 | M86: =IF(COUNTA(J86:L86)<3,"",IF(COUNTIF(J86:L86,"유지")=3,"채택","제외"))
A87: 86 | B87: Logos(논리) | C87: profitability | D87: accumulate | E87: 누적 | F87: 누적/NNG | G87: 누적/NNG | M87: =IF(COUNTA(J87:L87)<3,"",IF(COUNTIF(J87:L87,"유지")=3,"채택","제외"))
A88: 87 | B88: Logos(논리) | C88: profitability | D88: asset | E88: 자산 | F88: 자산/NNG | G88: 자산/NNG | M88: =IF(COUNTA(J88:L88)<3,"",IF(COUNTIF(J88:L88,"유지")=3,"채택","제외"))
A89: 88 | B89: Logos(논리) | C89: profitability | D89: loss | E89: 손실 | F89: 손실/NNG | G89: 손실/NNG | M89: =IF(COUNTA(J89:L89)<3,"",IF(COUNTIF(J89:L89,"유지")=3,"채택","제외"))
A90: 89 | B90: Logos(논리) | C90: profitability | D90: compensation | E90: 보수 | F90: 보수/NNG | G90: 보수/NNG | M90: =IF(COUNTA(J90:L90)<3,"",IF(COUNTIF(J90:L90,"유지")=3,"채택","제외"))
A91: 90 | B91: Logos(논리) | C91: profitability | D91: refund | E91: 환불 | F91: 환불/NNG | G91: 환불/NNG | M91: =IF(COUNTA(J91:L91)<3,"",IF(COUNTIF(J91:L91,"유지")=3,"채택","제외"))
A92: 91 | B92: Logos(논리) | C92: profitability | D92: transaction | E92: 거래 | F92: 거래/NNG | G92: 거래/NNG | H92: 차원내 중복 | M92: =IF(COUNTA(J92:L92)<3,"",IF(COUNTIF(J92:L92,"유지")=3,"채택","제외"))
A93: 92 | B93: Logos(논리) | C93: profitability | D93: hedge | E93: 헤지 | F93: 헤지/NNG | G93: 헤지/NNG | M93: =IF(COUNTA(J93:L93)<3,"",IF(COUNTIF(J93:L93,"유지")=3,"채택","제외"))
A94: 93 | B94: Logos(논리) | C94: profitability | D94: tax | E94: 세금 | F94: 세금/NNG | G94: 세금/NNG | M94: =IF(COUNTA(J94:L94)<3,"",IF(COUNTIF(J94:L94,"유지")=3,"채택","제외"))
A95: 94 | B95: Logos(논리) | C95: profitability | D95: amortize | E95: 상각 | F95: 상각/NNG | G95: 상각/NNG | M95: =IF(COUNTA(J95:L95)<3,"",IF(COUNTIF(J95:L95,"유지")=3,"채택","제외"))
A96: 95 | B96: Logos(논리) | C96: profitability | D96: annuity | E96: 연금 | F96: 연금/NNG | G96: 연금/NNG | M96: =IF(COUNTA(J96:L96)<3,"",IF(COUNTIF(J96:L96,"유지")=3,"채택","제외"))
A97: 96 | B97: Logos(논리) | C97: profitability | D97: amount | E97: 금액 | F97: 금액/NNG | G97: 금액/NNG | M97: =IF(COUNTA(J97:L97)<3,"",IF(COUNTIF(J97:L97,"유지")=3,"채택","제외"))
A98: 97 | B98: Logos(논리) | C98: profitability | D98: capita | E98: 1인당 | F98: 1/SN + 인/NNG + 당/XSN | G98: 1/SN + 인/NNG | H98: 구(句) 매칭 | M98: =IF(COUNTA(J98:L98)<3,"",IF(COUNTIF(J98:L98,"유지")=3,"채택","제외"))
A99: 98 | B99: Logos(논리) | C99: profitability | D99: bonds | E99: 채권 | F99: 채권/NNG | G99: 채권/NNG | M99: =IF(COUNTA(J99:L99)<3,"",IF(COUNTIF(J99:L99,"유지")=3,"채택","제외"))
A100: 99 | B100: Logos(논리) | C100: profitability | D100: balance sheet | E100: 재무상태표 | F100: 재무상태표/NNP | G100: 재무상태표/NNP | M100: =IF(COUNTA(J100:L100)<3,"",IF(COUNTIF(J100:L100,"유지")=3,"채택","제외"))
A101: 100 | B101: Logos(논리) | C101: profitability | D101: bankrupt | E101: 파산 | F101: 파산/NNG | G101: 파산/NNG | M101: =IF(COUNTA(J101:L101)<3,"",IF(COUNTIF(J101:L101,"유지")=3,"채택","제외"))
A102: 101 | B102: Logos(논리) | C102: profitability | D102: purchase | E102: 구매 | F102: 구매/NNG | G102: 구매/NNG | M102: =IF(COUNTA(J102:L102)<3,"",IF(COUNTIF(J102:L102,"유지")=3,"채택","제외"))
...

Sheet 고유키_요약
A1: 차원 | B1: 매칭 키 | C1: 한국어 표기 | D1: 원어 수 | E1: 원어(Table II) | F1: 자동 플래그 | G1: 검토 메모
A2: Logos(논리) | B2: 1/SN + 인/NNG | C2: 1인당 | D2: 1 | E2: capita | F2: 구(句) 매칭
A3: Logos(논리) | B3: EBITDA/SL | C3: EBITDA | D3: 1 | E3: EBITDA
A4: Logos(논리) | B4: 가격/NNG | C4: 가격 | D4: 1 | E4: price
A5: Logos(논리) | B5: 가동/NNG | C5: 가동 | D5: 1 | E5: operate
A6: Logos(논리) | B6: 가이드/NNG | C6: 가이드 | D6: 1 | E6: guide
A7: Logos(논리) | B7: 가치/NNG | C7: 가치 | D7: 1 | E7: valuable | F7: 차원충돌:ethos·logos | G7: logos(valuable)·ethos(worthy) 양쪽; '가치사슬' 등 과잉매칭
A8: Logos(논리) | B8: 가치/NNG + 있/VV | C8: 가치 있는 | D8: 1 | E8: worthwhile | F8: 구(句) 매칭
A9: Logos(논리) | B9: 감소/NNG | C9: 감소 | D9: 1 | E9: reduce
A10: Logos(논리) | B10: 개발/NNG | C10: 개발 | D10: 1 | E10: develop
A11: Logos(논리) | B11: 개선/NNG | C11: 개선 | D11: 1 | E11: improve
A12: Logos(논리) | B12: 개연/NNG | C12: 개연성 | D12: 1 | E12: probable
A13: Logos(논리) | B13: 객관/NNG | C13: 객관 | D13: 1 | E13: objective
A14: Logos(논리) | B14: 거래/NNG | C14: 거래 | D14: 2 | E14: transaction, deal | F14: 차원내 중복
A15: Logos(논리) | B15: 거래소/NNG | C15: 거래소 | D15: 1 | E15: exchange
A16: Logos(논리) | B16: 건전/NNG | C16: 건전 | D16: 1 | E16: sane | F16: 차원충돌:ethos·logos | G16: logos(sane)·ethos(wholesome) 양쪽; '재무 건전성'은 logos
A17: Logos(논리) | B17: 건전/NNG + 판단/NNG | C17: 건전한 판단 | D17: 1 | E17: sound-judgment | F17: 구(句) 매칭
A18: Logos(논리) | B18: 검증/NNG | C18: 검증 | D18: 1 | E18: verifiable
A19: Logos(논리) | B19: 결과/NNG | C19: 결과 | D19: 1 | E19: consequence
A20: Logos(논리) | B20: 결실/NNG | C20: 결실 | D20: 1 | E20: fruitful
A21: Logos(논리) | B21: 결함/NNG | C21: 결함 | D21: 1 | E21: deficiency
A22: Logos(논리) | B22: 경제/NNG | C22: 경제 | D22: 1 | E22: economic
A23: Logos(논리) | B23: 계약/NNG | C23: 계약 | D23: 1 | E23: contract
A24: Logos(논리) | B24: 계정/NNG | C24: 계정 | D24: 1 | E24: account
A25: Logos(논리) | B25: 계획/NNG | C25: 계획 | D25: 1 | E25: plan
A26: Logos(논리) | B26: 고/XPN + 수익/NNG | C26: 고수익 | D26: 2 | E26: lucrative, well-paying | F26: 구(句) 매칭, 차원내 중복
A27: Logos(논리) | B27: 고도/NNG | C27: 고도화 | D27: 1 | E27: advance | G27: advance. 한국 사업계획서 특유 빈출어 → logos
A28: Logos(논리) | B28: 고정/NNG | C28: 고정 | D28: 1 | E28: fix
A29: Logos(논리) | B29: 공급/NNG | C29: 공급 | D29: 1 | E29: supply
A30: Logos(논리) | B30: 공식/NNG | C30: 공식 | D30: 1 | E30: formula
A31: Logos(논리) | B31: 공정/NNG | C31: 공정 | D31: 1 | E31: process | F31: 차원충돌:ethos·logos | G31: 동음이의: 工程(제조 공정=logos) vs 公正(공정하다=ethos). '공정+하(XSA)'면 公正으로 분리 가능
A32: Logos(논리) | B32: 공학/NNG | C32: 공학 | D32: 1 | E32: engineering
A33: Logos(논리) | B33: 과학/NNG | C33: 과학 | D33: 1 | E33: scientific
A34: Logos(논리) | B34: 관심/NNG | C34: 관심 | D34: 1 | E34: interest | G34: interest(logos/scientific) 번역 중 '관심'은 오히려 정서적 → '이자'만 유지 고려
A35: Logos(논리) | B35: 관찰/NNG | C35: 관찰 | D35: 1 | E35: observe
A36: Logos(논리) | B36: 관행/NNG | C36: 관행 | D36: 1 | E36: practice
A37: Logos(논리) | B37: 교육/NNG | C37: 교육 | D37: 1 | E37: educate
A38: Logos(논리) | B38: 교환/NNG | C38: 교환 | D38: 1 | E38: exchange
A39: Logos(논리) | B39: 구매/NNG | C39: 구매 | D39: 1 | E39: purchase
A40: Logos(논리) | B40: 구조/NNG | C40: 구조 | D40: 1 | E40: structure
A41: Logos(논리) | B41: 구조/NNG + 조정/NNG | C41: 구조조정 | D41: 1 | E41: restructure | F41: 구(句) 매칭
A42: Logos(논리) | B42: 귀납/NNG | C42: 귀납 | D42: 1 | E42: inductive
A43: Logos(논리) | B43: 귀중/XR | C43: 귀중 | D43: 1 | E43: invaluable
A44: Logos(논리) | B44: 규율/NNG | C44: 규율 | D44: 1 | E44: discipline
A45: Logos(논리) | B45: 규제/NNG | C45: 규제 | D45: 1 | E45: regulate
A46: Logos(논리) | B46: 규칙/NNG | C46: 규칙 | D46: 1 | E46: rule
A47: Logos(논리) | B47: 균일/NNG | C47: 균일 | D47: 1 | E47: uniform
A48: Logos(논리) | B48: 근거/NNG | C48: 근거 | D48: 1 | E48: reason
A49: Logos(논리) | B49: 근거/NNG + 있/VA | C49: 근거 있는 | D49: 1 | E49: well-founded | F49: 구(句) 매칭
A50: Logos(논리) | B50: 근거/NNG + 탄탄/XR | C50: 근거 탄탄 | D50: 1 | E50: well-grounded | F50: 구(句) 매칭
A51: Logos(논리) | B51: 금액/NNG | C51: 금액 | D51: 1 | E51: amount
A52: Logos(논리) | B52: 금융/NNG | C52: 금융 | D52: 1 | E52: finance
A53: Logos(논리) | B53: 급여/NNG | C53: 급여 | D53: 1 | E53: pay
A54: Logos(논리) | B54: 기금/NNG | C54: 기금 | D54: 1 | E54: endowment
A55: Logos(논리) | B55: 기능/NNG | C55: 기능 | D55: 1 | E55: function
A56: Logos(논리) | B56: 기법/NNG | C56: 기법 | D56: 1 | E56: technique
A57: Logos(논리) | B57: 기술/NNG | C57: 기술, 기술적 | D57: 2 | E57: technology, technical | F57: 차원내 중복 | G57: technology. DIPS 사업계획서 최빈어 중 하나 → 비율 왜곡 가능, 별도 통제 고려
A58: Logos(논리) | B58: 기회/NNG | C58: 기회 | D58: 1 | E58: opportunity
A59: Logos(논리) | B59: 꼼꼼/MAG | C59: 꼼꼼 | D59: 1 | E59: meticulous
A60: Logos(논리) | B60: 꾸준/XR | C60: 꾸준 | D60: 1 | E60: steady
A61: Logos(논리) | B61: 냉철/XR | C61: 냉철 | D61: 1 | E61: sober
A62: Logos(논리) | B62: 논거/NNG | C62: 논거 | D62: 1 | E62: well-argued
A63: Logos(논리) | B63: 논리/NNG | C63: 논리 | D63: 1 | E63: logic
A64: Logos(논리) | B64: 누적/NNG | C64: 누적 | D64: 1 | E64: accumulate
A65: Logos(논리) | B65: 능력/NNG | C65: 능력 | D65: 1 | E65: ability
A66: Logos(논리) | B66: 능숙/XR | C66: 능숙 | D66: 1 | E66: adept
A67: Logos(논리) | B67: 단계/NNG | C67: 단계적 | D67: 1 | E67: step-by-step
A68: Logos(논리) | B68: 달러/NNG | C68: 달러 | D68: 1 | E68: dollar
A69: Logos(논리) | B69: 달성/NNG | C69: 달성 | D69: 1 | E69: achieve
A70: Logos(논리) | B70: 담보/NNG | C70: 담보 | D70: 1 | E70: collateral
A71: Logos(논리) | B71: 당좌/NNG + 대월/NNG | C71: 당좌대월 | D71: 1 | E71: overdraft | F71: 구(句) 매칭
A72: Logos(논리) | B72: 대출/NNG | C72: 대출 | D72: 1 | E72: loan
A73: Logos(논리) | B73: 더/MAG + 낫/VA | C73: 더 나은 | D73: 1 | E73: better | F73: 구(句) 매칭
A74: Logos(논리) | B74: 데이터/NNG | C74: 데이터 | D74: 1 | E74: data
A75: Logos(논리) | B75: 도움/NNG + 되/VV | C75: 도움이 되는 | D75: 1 | E75: conducive | F75: 구(句) 매칭
A76: Logos(논리) | B76: 도표/NNG | C76: 도표 | D76: 1 | E76: tabulation
A77: Logos(논리) | B77: 돈/NNG | C77: 돈 | D77: 1 | E77: money | F77: 1음절(과잉매칭)
A78: Logos(논리) | B78: 디자인/NNG | C78: 디자인 | D78: 1 | E78: design
A79: Logos(논리) | B79: 루틴/NNG | C79: 루틴 | D79: 1 | E79: routine
A80: Logos(논리) | B80: 리스/NNP | C80: 리스 | D80: 1 | E80: lease
A81: Logos(논리) | B81: 마진/NNG | C81: 마진 | D81: 1 | E81: margin
A82: Logos(논리) | B82: 맞춤/NNG | C82: 맞춤 | D82: 1 | E82: customize
A83: Logos(논리) | B83: 매출/NNG | C83: 매출 | D83: 2 | E83: sale, revenue | F83: 차원내 중복
A84: Logos(논리) | B84: 매출/NNG + 채권/NNG | C84: 매출채권 | D84: 1 | E84: receivable | F84: 구(句) 매칭
A85: Logos(논리) | B85: 명시/NNG | C85: 명시 | D85: 1 | E85: specified
A86: Logos(논리) | B86: 모델/NNG | C86: 모델 | D86: 1 | E86: model
A87: Logos(논리) | B87: 모드/NNG | C87: 모드 | D87: 1 | E87: mode
A88: Logos(논리) | B88: 목표/NNG | C88: 목표 | D88: 1 | E88: objective | G88: objective 번역. '목표'는 logos로 무난하나 원어 의도(객관성)와 다름
A89: Logos(논리) | B89: 무역/NNG | C89: 무역 | D89: 1 | E89: trade
A90: Logos(논리) | B90: 무조건/MAG | C90: 무조건 | D90: 1 | E90: unconditional
A91: Logos(논리) | B91: 물류/NNG | C91: 물류 | D91: 1 | E91: logistic
A92: Logos(논리) | B92: 바람직/XR | C92: 바람직 | D92: 1 | E92: advisable
A93: Logos(논리) | B93: 방법/NNG | C93: 방법 | D93: 1 | E93: method
A94: Logos(논리) | B94: 방식/NNG | C94: 방식 | D94: 1 | E94: method
A95: Logos(논리) | B95: 배당/NNG | C95: 배당 | D95: 1 | E95: dividend
A96: Logos(논리) | B96: 배분/NNG | C96: 배분 | D96: 1 | E96: allocate
A97: Logos(논리) | B97: 배정/NNG | C97: 배정 | D97: 1 | E97: assign
A98: Logos(논리) | B98: 배치/NNG | C98: 배치 | D98: 1 | E98: lay-out
A99: Logos(논리) | B99: 법칙/NNG | C99: 법칙 | D99: 1 | E99: laws
A100: Logos(논리) | B100: 변수/NNG | C100: 변수 | D100: 1 | E100: variable
...

Sheet 집계
A1: 차원 | B1: Table II 원어 수 | C1: 한국어 후보 행 수 | D1: 고유 매칭 키 수 | E1: 플래그·메모 있는 행 | F1: 평정 완료 행 | G1: 채택(만장일치)
A2: Logos(논리) | B2: 301 | C2: =COUNTIF(후보사전_원어별!$B$2:$B$963,A2) -> 340 | D2: =COUNTIF(고유키_요약!$A$2:$A$815,A2) -> 318 | E2: =COUNTIFS(후보사전_원어별!$B$2:$B$963,A2,후보사전_원어별!$H$2:$H$963,"?*")+COUNTIFS(후보사전_원어별!$B$2:$B$963,A2,후보사전_원어별!$H$2:$H$963,"",후보사전_원어별!$I$2:$I$963,"?*") -> 80 | F2: =COUNTIFS(후보사전_원어별!$B$2:$B$963,A2,후보사전_원어별!$M$2:$M$963,"채택")+COUNTIFS(후보사전_원어별!$B$2:$B$963,A2,후보사전_원어별!$M$2:$M$963,"제외") -> 0 | G2: =COUNTIFS(후보사전_원어별!$B$2:$B$963,A2,후보사전_원어별!$M$2:$M$963,"채택") -> 0
A3: Pathos(감정) | B3: 327 | C3: =COUNTIF(후보사전_원어별!$B$2:$B$963,A3) -> 340 | D3: =COUNTIF(고유키_요약!$A$2:$A$815,A3) -> 268 | E3: =COUNTIFS(후보사전_원어별!$B$2:$B$963,A3,후보사전_원어별!$H$2:$H$963,"?*")+COUNTIFS(후보사전_원어별!$B$2:$B$963,A3,후보사전_원어별!$H$2:$H$963,"",후보사전_원어별!$I$2:$I$963,"?*") -> 152 | F3: =COUNTIFS(후보사전_원어별!$B$2:$B$963,A3,후보사전_원어별!$M$2:$M$963,"채택")+COUNTIFS(후보사전_원어별!$B$2:$B$963,A3,후보사전_원어별!$M$2:$M$963,"제외") -> 0 | G3: =COUNTIFS(후보사전_원어별!$B$2:$B$963,A3,후보사전_원어별!$M$2:$M$963,"채택") -> 0
A4: Ethos(성품) | B4: 262 | C4: =COUNTIF(후보사전_원어별!$B$2:$B$963,A4) -> 282 | D4: =COUNTIF(고유키_요약!$A$2:$A$815,A4) -> 228 | E4: =COUNTIFS(후보사전_원어별!$B$2:$B$963,A4,후보사전_원어별!$H$2:$H$963,"?*")+COUNTIFS(후보사전_원어별!$B$2:$B$963,A4,후보사전_원어별!$H$2:$H$963,"",후보사전_원어별!$I$2:$I$963,"?*") -> 131 | F4: =COUNTIFS(후보사전_원어별!$B$2:$B$963,A4,후보사전_원어별!$M$2:$M$963,"채택")+COUNTIFS(후보사전_원어별!$B$2:$B$963,A4,후보사전_원어별!$M$2:$M$963,"제외") -> 0 | G4: =COUNTIFS(후보사전_원어별!$B$2:$B$963,A4,후보사전_원어별!$M$2:$M$963,"채택") -> 0
A5: 합계 | B5: =SUM(B2:B4) -> 890 | C5: =SUM(C2:C4) -> 962 | D5: =SUM(D2:D4) -> 814 | E5: =SUM(E2:E4) -> 363 | F5: =SUM(F2:F4) -> 0 | G5: =SUM(G2:G4) -> 0
A7: Table II 원어 수는 원문에서 전사한 값(하드코딩; 원문 보고치 891).
